galaxy_tool_shed-25.0.3.dist-info/licenses/LICENSE
tool_shed/__init__.py
tool_shed/context.py
tool_shed/py.typed
tool_shed/repository_registry.py
tool_shed/structured_app.py
tool_shed/dependencies/__init__.py
tool_shed/dependencies/attribute_handlers.py
tool_shed/dependencies/repository/__init__.py
tool_shed/dependencies/repository/relation_builder.py
tool_shed/dependencies/tool/__init__.py
tool_shed/dependencies/tool/tag_attribute_handler.py
tool_shed/galaxy_install/__init__.py
tool_shed/grids/__init__.py
tool_shed/grids/admin_grids.py
tool_shed/grids/repository_grid_filter_manager.py
tool_shed/grids/repository_grids.py
tool_shed/grids/util.py
tool_shed/managers/__init__.py
tool_shed/managers/categories.py
tool_shed/managers/groups.py
tool_shed/managers/model_cache.py
tool_shed/managers/repositories.py
tool_shed/managers/tools.py
tool_shed/managers/trs.py
tool_shed/managers/users.py
tool_shed/metadata/__init__.py
tool_shed/metadata/repository_metadata_manager.py
tool_shed/repository_types/__init__.py
tool_shed/repository_types/metadata.py
tool_shed/repository_types/registry.py
tool_shed/repository_types/repository_suite_definition.py
tool_shed/repository_types/tool_dependency_definition.py
tool_shed/repository_types/unrestricted.py
tool_shed/repository_types/util.py
tool_shed/test/__init__.py
tool_shed/test/conftest.py
tool_shed/test/base/__init__.py
tool_shed/test/base/api.py
tool_shed/test/base/api_util.py
tool_shed/test/base/browser.py
tool_shed/test/base/common.py
tool_shed/test/base/driver.py
tool_shed/test/base/playwrightbrowser.py
tool_shed/test/base/populators.py
tool_shed/test/base/test_db_util.py
tool_shed/test/base/twillbrowser.py
tool_shed/test/base/twilltestcase.py
tool_shed/test/functional/__init__.py
tool_shed/test/functional/conftest.py
tool_shed/test/functional/test_0000_basic_repository_features.py
tool_shed/test/functional/test_0010_repository_with_tool_dependencies.py
tool_shed/test/functional/test_0020_basic_repository_dependencies.py
galaxy_tool_shed-25.0.3.dist-info/METADATA
galaxy_tool_shed-25.0.3.dist-info/WHEEL
galaxy_tool_shed-25.0.3.dist-info/top_level.txt
galaxy_tool_shed-25.0.3.dist-info/RECORD
